PricingEngine-0.0.5b0.dist-info/METADATA
PricingEngine-0.0.5b0.dist-info/RECORD
PricingEngine-0.0.5b0.dist-info/WHEEL
PricingEngine-0.0.5b0.dist-info/entry_points.txt
PricingEngine-0.0.5b0.dist-info/top_level.txt
logger/__init__.py
logger/logger_helper.py
source/__init__.py
source/algorithm/__init__.py
source/algorithm/scikit_learn/__init__.py
source/algorithm/scikit_learn/regrassion_fine_tune.py
source/algorithm/scikit_learn/regression.py
source/controller/__init__.py
source/controller/pricing_engine.py
source/interface/__init__.py
source/interface/pricing_engine_interface.py
source/model/__init__.py
source/model/algorithms.py
source/model/car.py
source/model/data_analysis.py
source/model/data_writer.py
source/model/get_user_data.py
source/model/prediction.py
source/model/pricing_data_reader.py
source/model/user_data_label_encode.py
source/model/vin_decode.py
source/webapp/__init__.py
source/webservice/__init__.py
source/webservice/get_prediction.py
tests/__init__.py
tests/algorithm_test.py
tests/data_writer_test.py
tests/prediction_test.py
tests/pricing_data_reader_test.py
tests/regrassion_test.py
tests/vin_decode_test.py
utilities/__init__.py
utilities/app_history.py
utilities/cars.py
utilities/constants.py
utilities/db_helper.py
utilities/helper.py
utilities/query_sql.py
